{"СвЮЛ":{"@attributes":{"ДатаВып":"2025-01-27","ОГРН":"1167232093181","ДатаОГРН":"2016-12-15","ИНН":"7203405421","КПП":"720301001","СпрОПФ":"ОКОПФ","КодОПФ":"12300","ПолнНаимОПФ":"Общества с ограниченной ответственностью"},"СвНаимЮЛ":{"@attributes":{"НаимЮЛПолн":"ОБЩЕСТВО С ОГРАНИЧЕННОЙ ОТВЕТСТВЕННОСТЬЮ \"ПРОИЗВОДСТВЕННО-ТЕХНИЧЕСКИЙ КОМБИНАТ\""},"ГРНДата":{"@attributes":{"ГРН":"1167232093181","ДатаЗаписи":"2016-12-15"}},"СвНаимЮЛСокр":{"@attributes":{"НаимСокр":"ООО \"ПТК\""},"ГРНДата":{"@attributes":{"ГРН":"1167232093181","ДатаЗаписи":"2016-12-15"}}}},"СвАдресЮЛ":{"@attributes":{"ВидАдрКлассиф":"2"},"АдресРФ":{"@attributes":{"Индекс":"625017","КодРегион":"72","КодАдрКладр":"720000010000324","Дом":"Д. 12"},"Регион":{"@attributes":{"НаимРегион":"ТЮМЕНСКАЯ ОБЛАСТЬ"}},"Город":{"@attributes":{"ТипГород":"Г.","НаимГород":"ТЮМЕНЬ"}},"Улица":{"@attributes":{"ТипУлица":"УЛ.","НаимУлица":"АВТОРЕМОНТНАЯ"}},"ГРНДата":{"@attributes":{"ГРН":"1167232093181","ДатаЗаписи":"2016-12-15"}}}},"СвОбрЮЛ":{"@attributes":{"ОГРН":"1167232093181","ДатаОГРН":"2016-12-15"},"СпОбрЮЛ":{"@attributes":{"КодСпОбрЮЛ":"21","НаимСпОбрЮЛ":"Создание юридического лица путем реорганизации в форме преобразования"}},"ГРНДата":{"@attributes":{"ГРН":"1167232093181","ДатаЗаписи":"2016-12-15"}}},"СвРегОрг":{"@attributes":{"КодНО":"7232","НаимНО":"Межрайонная инспекция Федеральной налоговой службы № 14 по Тюменской области","АдрРО":",625009,,, Тюмень г,, Товарное шоссе ул, д 15,,"},"ГРНДата":{"@attributes":{"ГРН":"1167232093181","ДатаЗаписи":"2016-12-15"}}},"СвУчетНО":{"@attributes":{"ИНН":"7203405421","КПП":"720301001","ДатаПостУч":"2016-12-15"},"СвНО":{"@attributes":{"КодНО":"7203","НаимНО":"Инспекция Федеральной налоговой службы по г. Тюмени № 3"}},"ГРНДата":{"@attributes":{"ГРН":"2167232713679","ДатаЗаписи":"2016-12-15"}}},"СвРегПФ":{"@attributes":{"РегНомПФ":"1112520067","ДатаРег":"2016-12-19"},"СвОргПФ":{"@attributes":{"КодПФ":"072","НаимПФ":"Отделение Фонда пенсионного и социального страхования Российской Федерации по Тюменской области"}},"ГРНДата":{"@attributes":{"ГРН":"2257200342750","ДатаЗаписи":"2025-01-27"}}},"СвРегФСС":{"@attributes":{"РегНомФСС":"1112520067","ДатаРег":"2016-12-19"},"СвОргФСС":{"@attributes":{"КодФСС":"072","НаимФСС":"Отделение Фонда пенсионного и социального страхования Российской Федерации по Тюменской области"}},"ГРНДата":{"@attributes":{"ГРН":"2257200342760","ДатаЗаписи":"2025-01-27"}}},"СвУстКап":{"@attributes":{"НаимВидКап":"УСТАВНЫЙ КАПИТАЛ","СумКап":"3400000"},"ГРНДата":{"@attributes":{"ГРН":"1167232093181","ДатаЗаписи":"2016-12-15"}}},"СведДолжнФЛ":{"ГРНДатаПерв":{"@attributes":{"ГРН":"2217200200897","ДатаЗаписи":"2021-06-30"}},"СвФЛ":{"@attributes":{"Фамилия":"ОТРАДНОВ","Имя":"ИГОРЬ","Отчество":"АНАТОЛЬЕВИЧ","ИННФЛ":"720400008091"},"ГРНДата":{"@attributes":{"ГРН":"2217200200897","ДатаЗаписи":"2021-06-30"}}},"СвДолжн":{"@attributes":{"ВидДолжн":"02","НаимВидДолжн":"Руководитель юридического лица","НаимДолжн":"ДИРЕКТОР"},"ГРНДата":{"@attributes":{"ГРН":"2217200200897","ДатаЗаписи":"2021-06-30"}}},"СвПолФЛ":{"@attributes":{"Пол":"1"},"ГРНДата":{"@attributes":{"ГРН":"2217200200897","ДатаЗаписи":"2021-06-30"}}},"СвГраждФЛ":{"@attributes":{"КодГражд":"1"},"ГРНДата":{"@attributes":{"ГРН":"2217200200897","ДатаЗаписи":"2021-06-30"}}}},"СвУчредит":{"УчрФЛ":{"ГРНДатаПерв":{"@attributes":{"ГРН":"2217200184617","ДатаЗаписи":"2021-06-17"}},"СвФЛ":{"@attributes":{"Фамилия":"ОТРАДНОВ","Имя":"ИГОРЬ","Отчество":"АНАТОЛЬЕВИЧ","ИННФЛ":"720400008091"},"ГРНДата":{"@attributes":{"ГРН":"2217200184617","ДатаЗаписи":"2021-06-17"}}},"СвПолФЛ":{"@attributes":{"Пол":"1"},"ГРНДата":{"@attributes":{"ГРН":"2217200184617","ДатаЗаписи":"2021-06-17"}}},"СвГраждФЛ":{"@attributes":{"КодГражд":"1"},"ГРНДата":{"@attributes":{"ГРН":"2217200184617","ДатаЗаписи":"2021-06-17"}}},"ДоляУстКап":{"@attributes":{"НоминСтоим":"3400000"},"РазмерДоли":{"Процент":"100"},"ГРНДата":{"@attributes":{"ГРН":"2217200184617","ДатаЗаписи":"2021-06-17"}}}}},"СвОКВЭД":{"СвОКВЭДОсн":{"@attributes":{"КодОКВЭД":"45.20.2","НаимОКВЭД":"Техническое обслуживание и ремонт прочих автотранспортных средств","ПрВерсОКВЭД":"2014"},"ГРНДата":{"@attributes":{"ГРН":"1167232093181","ДатаЗаписи":"2016-12-15"}}},"СвОКВЭДДоп":[{"@attributes":{"КодОКВЭД":"45.20.1","НаимОКВЭД":"Техническое обслуживание и ремонт легковых автомобилей и легких грузовых автотранспортных средств","ПрВерсОКВЭД":"2014"},"ГРНДата":{"@attributes":{"ГРН":"1167232093181","ДатаЗаписи":"2016-12-15"}}},{"@attributes":{"КодОКВЭД":"45.32","НаимОКВЭД":"Торговля розничная автомобильными деталями, узлами и принадлежностями","ПрВерсОКВЭД":"2014"},"ГРНДата":{"@attributes":{"ГРН":"1167232093181","ДатаЗаписи":"2016-12-15"}}},{"@attributes":{"КодОКВЭД":"49.41.2","НаимОКВЭД":"Перевозка грузов неспециализированными автотранспортными средствами","ПрВерсОКВЭД":"2014"},"ГРНДата":{"@attributes":{"ГРН":"1167232093181","ДатаЗаписи":"2016-12-15"}}},{"@attributes":{"КодОКВЭД":"68.20","НаимОКВЭД":"Аренда и управление собственным или арендованным недвижимым имуществом","ПрВерсОКВЭД":"2014"},"ГРНДата":{"@attributes":{"ГРН":"2237200307892","ДатаЗаписи":"2023-09-18"}}}]},"СвЛицензия":{"@attributes":{"НомЛиц":"ВХ-57 016030 Переоформ","ДатаЛиц":"2017-01-13","ДатаНачЛиц":"2017-01-13"},"НаимЛицВидДеят":"Эксплуатация взрывопожароопасных и химически опасных производственных объектов I, II и III классов опасности","ЛицОргВыдЛиц":"Северо-Уральское управление Федеральной службы по экологическому, технологическому и атомному надзору","ГРНДата":{"@attributes":{"ГРН":"2177232041897","ДатаЗаписи":"2017-01-18"}}},"СвПредш":{"@attributes":{"ОГРН":"1027200791177","ИНН":"7204039305","НаимЮЛПолн":"ЗАКРЫТОЕ АКЦИОНЕРНОЕ ОБЩЕСТВО \"ПРОИЗВОДСТВЕННО - ТЕХНИЧЕСКИЙ КОМБИНАТ\""},"ГРНДата":{"@attributes":{"ГРН":"1167232093181","ДатаЗаписи":"2016-12-15"}}},"СвЗапЕГРЮЛ":[{"@attributes":{"ИдЗап":"150000114071852","ГРН":"1167232093181","ДатаЗап":"2016-12-15"},"ВидЗап":{"@attributes":{"КодСПВЗ":"11301","НаимВидЗап":"Создание юридического лица путем реорганизации в форме преобразования"}},"СвРегОрг":{"@attributes":{"КодНО":"7232","НаимНО":"Межрайонная инспекция Федеральной налоговой службы № 14 по Тюменской области"}},"СведПредДок":[{"НаимДок":"Р12001 ЗАЯВЛЕНИЕ О СОЗДАНИИ ЮЛ ПРИ РЕОРГАНИЗАЦИИ"},{"НаимДок":"ДОКУМЕНТ ОБ ОПЛАТЕ ГОСУДАРСТВЕННОЙ ПОШЛИНЫ","ДатаДок":"2016-12-07"},{"НаимДок":"РЕШЕНИЕ","ДатаДок":"2016-12-07"},{"НаимДок":"РЕШЕНИЕ","ДатаДок":"2016-09-05"},{"НаимДок":"ПЕРЕДАТОЧНЫЙ АКТ","ДатаДок":"2016-12-07"},{"НаимДок":"СПИСОК"},{"НаимДок":"УСТАВ ЮЛ"},{"НаимДок":"ОПРОСНЫЙ ЛИСТ"}],"СвСвид":{"@attributes":{"Серия":"72","Номер":"002506841","ДатаВыдСвид":"2016-12-16"}}},{"@attributes":{"ИдЗап":"150000114812501","ГРН":"2167232713679","ДатаЗап":"2016-12-15"},"ВидЗап":{"@attributes":{"КодСПВЗ":"13200","НаимВидЗап":"Представление сведений об учете юридического лица в налоговом органе"}},"СвРегОрг":{"@attributes":{"КодНО":"7232","НаимНО":"Межрайонная инспекция Федеральной налоговой службы № 14 по Тюменской области"}}},{"@attributes":{"ИдЗап":"150000115141543","ГРН":"2167232721005","ДатаЗап":"2016-12-20"},"ВидЗап":{"@attributes":{"КодСПВЗ":"13300","НаимВидЗап":"Представление сведений о регистрации юридического лица в качестве страхователя в территориальном органе Пенсионного фонда Российской Федерации"}},"СвРегОрг":{"@attributes":{"КодНО":"7232","НаимНО":"Межрайонная инспекция Федеральной налоговой службы № 14 по Тюменской области"}}},{"@attributes":{"ИдЗап":"150000115141637","ГРН":"2167232721269","ДатаЗап":"2016-12-20"},"ВидЗап":{"@attributes":{"КодСПВЗ":"13400","НаимВидЗап":"Представление сведений о регистрации юридического лица в качестве страхователя в исполнительном органе Фонда социального страхования Российской Федерации"}},"СвРегОрг":{"@attributes":{"КодНО":"7232","НаимНО":"Межрайонная инспекция Федеральной налоговой службы № 14 по Тюменской области"}}},{"@attributes":{"ИдЗап":"150000118155697","ГРН":"2177232041897","ДатаЗап":"2017-01-18"},"ВидЗап":{"@attributes":{"КодСПВЗ":"13102","НаимВидЗап":"Представление лицензирующим органом сведений о переоформлении лицензии, внесении изменений в сведения о лицензии (сведений о продлении срока действия лицензии)"}},"СвРегОрг":{"@attributes":{"КодНО":"7232","НаимНО":"Межрайонная инспекция Федеральной налоговой службы № 14 по Тюменской области"}}},{"@attributes":{"ИдЗап":"150000210079845","ГРН":"2207203011387","ДатаЗап":"2020-11-16"},"ВидЗап":{"@attributes":{"КодСПВЗ":"12101","НаимВидЗап":"Государственная регистрация изменений, внесенных в учредительный документ юридического лица, и внесение изменений в сведения о юридическом лице, содержащиеся в ЕГРЮЛ"}},"СвРегОрг":{"@attributes":{"КодНО":"7232","НаимНО":"Межрайонная инспекция Федеральной налоговой службы № 14 по Тюменской области"}},"СведПредДок":[{"НаимДок":"ИНОЙ ДОКУМ. В СООТВ.С ЗАКОНОДАТЕЛЬСТВОМ РФ"},{"НаимДок":"Р13001 ЗАЯВЛЕНИЕ ОБ ИЗМЕНЕНИЯХ, ВНОСИМЫХ В УЧРЕД.ДОКУМЕНТЫ"},{"НаимДок":"УСТАВ ЮЛ"},{"НаимДок":"РЕШЕНИЕ О ВНЕСЕНИИ ИЗМЕНЕНИЙ В УЧРЕДИТЕЛЬНЫЕ ДОКУМЕНТЫ","НомДок":"2","ДатаДок":"2020-10-14"}]},{"@attributes":{"ИдЗап":"150000225371431","ГРН":"2217200184617","ДатаЗап":"2021-06-17"},"ВидЗап":{"@attributes":{"КодСПВЗ":"12201","НаимВидЗап":"Изменение сведений о юридическом лице, содержащихся в Едином государственном реестре юридических лиц"}},"СвРегОрг":{"@attributes":{"КодНО":"7232","НаимНО":"Межрайонная инспекция Федеральной налоговой службы № 14 по Тюменской области"}},"СведПредДок":[{"НаимДок":"Р13014 Заявление об изменении учр.документа и/или иных сведений о ЮЛ"},{"НаимДок":"Иной докум. в соотв.с законодательством РФ"}]},{"@attributes":{"ИдЗап":"150000226049209","ГРН":"2217200200897","ДатаЗап":"2021-06-30"},"ВидЗап":{"@attributes":{"КодСПВЗ":"12201","НаимВидЗап":"Изменение сведений о юридическом лице, содержащихся в Едином государственном реестре юридических лиц"}},"СвРегОрг":{"@attributes":{"КодНО":"7232","НаимНО":"Межрайонная инспекция Федеральной налоговой службы № 14 по Тюменской области"}},"СведПредДок":[{"НаимДок":"Р13014 ЗАЯВЛЕНИЕ ОБ ИЗМЕНЕНИИ УЧР.ДОКУМЕНТА И/ИЛИ ИНЫХ СВЕДЕНИЙ О ЮЛ"},{"НаимДок":"РЕШЕНИЕ О ВНЕСЕНИИ ИЗМЕНЕНИЙ В УЧРЕДИТЕЛЬНЫЙ ДОКУМЕНТ ЮЛ, ЛИБО ИНОЕ РЕШЕНИЕ ИЛИ ДОКУМЕНТ, НА ОСНОВАНИИ КОТОРОГО ВНОСЯТСЯ ДАННЫЕ ИЗМЕНЕНИЯ","НомДок":"1","ДатаДок":"2021-06-21"},{"НаимДок":"СВИДЕТЕЛЬСТВО"}]},{"@attributes":{"ИдЗап":"150000287508641","ГРН":"2237200307892","ДатаЗап":"2023-09-18"},"ВидЗап":{"@attributes":{"КодСПВЗ":"12201","НаимВидЗап":"Изменение сведений о юридическом лице, содержащихся в Едином государственном реестре юридических лиц"}},"СвРегОрг":{"@attributes":{"КодНО":"7232","НаимНО":"Межрайонная инспекция Федеральной налоговой службы № 14 по Тюменской области"}},"СведПредДок":{"НаимДок":"Р13014 Заявление об изменении учр.документа и/или иных сведений о ЮЛ"}},{"@attributes":{"ИдЗап":"150000321377536","ГРН":"2257200342750","ДатаЗап":"2025-01-27"},"ВидЗап":{"@attributes":{"КодСПВЗ":"13301","НаимВидЗап":"Представление сведений о регистрации юридического лица в качестве страхователя в Социальном фонде Российской Федерации (обязательное пенсионное страхование)"}},"СвРегОрг":{"@attributes":{"КодНО":"7232","НаимНО":"Межрайонная инспекция Федеральной налоговой службы № 14 по Тюменской области"}},"СведПредДок":{"НаимДок":"Сведения о регистрации ЮЛ по ОПС","ДатаДок":"2025-01-23"}},{"@attributes":{"ИдЗап":"150000321377537","ГРН":"2257200342760","ДатаЗап":"2025-01-27"},"ВидЗап":{"@attributes":{"КодСПВЗ":"13401","НаимВидЗап":"Представление сведений о регистрации юридического лица в качестве страхователя в Социальном фонде Российской Федерации (обязательное социальное страхование)"}},"СвРегОрг":{"@attributes":{"КодНО":"7232","НаимНО":"Межрайонная инспекция Федеральной налоговой службы № 14 по Тюменской области"}},"СведПредДок":{"НаимДок":"Сведения о регистрации ЮЛ по ОСС","ДатаДок":"2025-01-23"}}]}}