{"СвЮЛ":{"@attributes":{"ДатаВып":"2025-04-03","ОГРН":"1027403903658","ДатаОГРН":"2002-12-31","ИНН":"7453050034","КПП":"745301001","СпрОПФ":"ОКОПФ","КодОПФ":"12300","ПолнНаимОПФ":"Общества с ограниченной ответственностью"},"СвНаимЮЛ":{"@attributes":{"НаимЮЛПолн":"ОБЩЕСТВО С ОГРАНИЧЕННОЙ ОТВЕТСТВЕННОСТЬЮ \"АСТЕРА\""},"ГРНДата":{"@attributes":{"ГРН":"1027403903658","ДатаЗаписи":"2002-12-31"}},"СвНаимЮЛСокр":{"@attributes":{"НаимСокр":"ООО \"АСТЕРА\""},"ГРНДата":{"@attributes":{"ГРН":"1027403903658","ДатаЗаписи":"2002-12-31"}}}},"СвАдресЮЛ":{"@attributes":{"ВидАдрКлассиф":"2"},"АдресРФ":{"@attributes":{"Индекс":"454080","КодРегион":"74","КодАдрКладр":"740000010000478","Дом":"Д. 75А","Кварт":"ОФИС 808"},"Регион":{"@attributes":{"НаимРегион":"ЧЕЛЯБИНСКАЯ ОБЛАСТЬ"}},"Город":{"@attributes":{"ТипГород":"Г","НаимГород":"ЧЕЛЯБИНСК"}},"Улица":{"@attributes":{"ТипУлица":"УЛ","НаимУлица":"СОНИ КРИВОЙ"}},"ГРНДата":{"@attributes":{"ГРН":"2157453118084","ДатаЗаписи":"2015-08-25"}},"ГРНДатаИспр":{"@attributes":{"ГРН":"2257401815383","ДатаЗаписи":"2025-02-14"}}},"СвНедАдресЮЛ":{"@attributes":{"ПризнНедАдресЮЛ":"2","ТекстНедАдресЮЛ":"сведения недостоверны (результаты проверки достоверности содержащихся в ЕГРЮЛ сведений о юридическом лице)"},"ГРНДата":{"@attributes":{"ГРН":"2247400318328","ДатаЗаписи":"2024-05-31"}}}},"СвОбрЮЛ":{"@attributes":{"ОГРН":"1027403903658","ДатаОГРН":"2002-12-31","РегНом":"11198","ДатаРег":"1998-12-07","НаимРО":"Администрация города Челябинска (Управление государственной регистрации города Челябинска)"},"СпОбрЮЛ":{"@attributes":{"КодСпОбрЮЛ":"01","НаимСпОбрЮЛ":"Создание юридического лица до 01.07.2002"}},"ГРНДата":{"@attributes":{"ГРН":"1027403903658","ДатаЗаписи":"2002-12-31"}},"ГРНДатаИспр":{"@attributes":{"ГРН":"2077453074664","ДатаЗаписи":"2007-03-31"}}},"СвРегОрг":{"@attributes":{"КодНО":"7456","НаимНО":"Межрайонная инспекция Федеральной налоговой службы № 17 по Челябинской области","АдрРО":",455038, Челябинская обл,, Магнитогорск г,, Карла Маркса пр-кт, д 158, корп 1,"},"ГРНДата":{"@attributes":{"ГРН":"2157453254055","ДатаЗаписи":"2015-12-18"}}},"СвСтатус":{"СвСтатус":{"@attributes":{"КодСтатусЮЛ":"415","НаимСтатусЮЛ":"Юридическое лицо прекращено в связи с исключением из ЕГРЮЛ (наличие в ЕГРЮЛ сведений о юридическом лице, в отношении которых внесена запись о недостоверности)"}},"ГРНДата":{"@attributes":{"ГРН":"2257402016408","ДатаЗаписи":"2025-04-03"}}},"СвПрекрЮЛ":{"@attributes":{"ДатаПрекрЮЛ":"2025-04-03"},"СпПрекрЮЛ":{"@attributes":{"КодСпПрекрЮЛ":"415","НаимСпПрекрЮЛ":"Исключение из ЕГРЮЛ юридического лица в связи наличием в ЕГРЮЛ сведений о нем, в отношении которых внесена запись о недостоверности"}},"СвРегОрг":{"@attributes":{"КодНО":"7456","НаимНО":"Межрайонная инспекция Федеральной налоговой службы № 17 по Челябинской области"}},"ГРНДата":{"@attributes":{"ГРН":"2257402016408","ДатаЗаписи":"2025-04-03"}}},"СвУчетНО":{"@attributes":{"ИНН":"7453050034","КПП":"745301001","ДатаПостУч":"1998-12-16"},"СвНО":{"@attributes":{"КодНО":"7453","НаимНО":"Межрайонная инспекция Федеральной налоговой службы № 28 по Челябинской области"}},"ГРНДата":{"@attributes":{"ГРН":"2257402017651","ДатаЗаписи":"2025-04-03"}}},"СвРегПФ":{"@attributes":{"РегНомПФ":"1045966767","ДатаРег":"1998-12-23"},"СвОргПФ":{"@attributes":{"КодПФ":"074","НаимПФ":"Отделение Фонда пенсионного и социального страхования Российской Федерации по Челябинской области"}},"ГРНДата":{"@attributes":{"ГРН":"2257401275833","ДатаЗаписи":"2025-02-09"}}},"СвРегФСС":{"@attributes":{"РегНомФСС":"1045966767","ДатаРег":"1998-12-18"},"СвОргФСС":{"@attributes":{"КодФСС":"074","НаимФСС":"Отделение Фонда пенсионного и социального страхования Российской Федерации по Челябинской области"}},"ГРНДата":{"@attributes":{"ГРН":"2257401275822","ДатаЗаписи":"2025-02-09"}}},"СвУстКап":{"@attributes":{"НаимВидКап":"УСТАВНЫЙ КАПИТАЛ","СумКап":"10000"},"ГРНДата":{"@attributes":{"ГРН":"2157453118084","ДатаЗаписи":"2015-08-25"}}},"СведДолжнФЛ":{"ГРНДатаПерв":{"@attributes":{"ГРН":"1027403903658","ДатаЗаписи":"2002-12-31"}},"СвФЛ":{"@attributes":{"Фамилия":"ШУВАХИН","Имя":"АРТЕМ","Отчество":"АНАТОЛЬЕВИЧ","ИННФЛ":"745108728751"},"ГРНДата":{"@attributes":{"ГРН":"2227400008680","ДатаЗаписи":"2022-01-01"}}},"СвДолжн":{"@attributes":{"ВидДолжн":"02","НаимВидДолжн":"Руководитель юридического лица","НаимДолжн":"ДИРЕКТОР"},"ГРНДата":{"@attributes":{"ГРН":"2227400008680","ДатаЗаписи":"2022-01-01"}}},"СвПолФЛ":{"@attributes":{"Пол":"1"},"ГРНДата":{"@attributes":{"ГРН":"2227400008680","ДатаЗаписи":"2022-01-01"}}},"СвГраждФЛ":{"@attributes":{"КодГражд":"1"},"ГРНДата":{"@attributes":{"ГРН":"2227400008680","ДатаЗаписи":"2022-01-01"}}}},"СвУчредит":{"УчрФЛ":{"ГРНДатаПерв":{"@attributes":{"ГРН":"1027403903658","ДатаЗаписи":"2002-12-31"}},"СвФЛ":{"@attributes":{"Фамилия":"ШУВАХИНА","Имя":"ВАЛЕРИЯ","Отчество":"АНАТОЛЬЕВНА","ИННФЛ":"745106393404"},"ГРНДата":{"@attributes":{"ГРН":"2227400008670","ДатаЗаписи":"2022-01-01"}}},"СвПолФЛ":{"@attributes":{"Пол":"2"},"ГРНДата":{"@attributes":{"ГРН":"2227400008670","ДатаЗаписи":"2022-01-01"}}},"СвГраждФЛ":{"@attributes":{"КодГражд":"1"},"ГРНДата":{"@attributes":{"ГРН":"2227400008670","ДатаЗаписи":"2022-01-01"}}},"ДоляУстКап":{"@attributes":{"НоминСтоим":"10000"},"РазмерДоли":{"Процент":"100"},"ГРНДата":{"@attributes":{"ГРН":"2197456888506","ДатаЗаписи":"2019-08-30"}}}}},"СвОКВЭД":{"СвОКВЭДОсн":{"@attributes":{"КодОКВЭД":"46.69.8","НаимОКВЭД":"Торговля оптовая техникой, оборудованием и инструментами, применяемыми в медицинских целях","ПрВерсОКВЭД":"2014"},"ГРНДата":{"@attributes":{"ГРН":"2197456353246","ДатаЗаписи":"2019-04-05"}}},"СвОКВЭДДоп":[{"@attributes":{"КодОКВЭД":"46.12","НаимОКВЭД":"Деятельность агентов по оптовой торговле топливом, рудами, металлами и химическими веществами","ПрВерсОКВЭД":"2014"},"ГРНДата":{"@attributes":{"ГРН":"2197456353246","ДатаЗаписи":"2019-04-05"}}},{"@attributes":{"КодОКВЭД":"46.18","НаимОКВЭД":"Деятельность агентов, специализирующихся на оптовой торговле прочими отдельными видами товаров","ПрВерсОКВЭД":"2014"},"ГРНДата":{"@attributes":{"ГРН":"2197456353246","ДатаЗаписи":"2019-04-05"}}},{"@attributes":{"КодОКВЭД":"46.18.11","НаимОКВЭД":"Деятельность агентов, специализирующихся на оптовой торговле фармацевтической продукцией","ПрВерсОКВЭД":"2014"},"ГРНДата":{"@attributes":{"ГРН":"2197456353246","ДатаЗаписи":"2019-04-05"}}},{"@attributes":{"КодОКВЭД":"46.18.12","НаимОКВЭД":"Деятельность агентов, специализирующихся на оптовой торговле изделиями, применяемыми в медицинских целях","ПрВерсОКВЭД":"2014"},"ГРНДата":{"@attributes":{"ГРН":"2197456353246","ДатаЗаписи":"2019-04-05"}}},{"@attributes":{"КодОКВЭД":"46.18.13","НаимОКВЭД":"Деятельность агентов, специализирующихся на оптовой торговле парфюмерными и косметическими товарами, включая мыло","ПрВерсОКВЭД":"2014"},"ГРНДата":{"@attributes":{"ГРН":"2197456353246","ДатаЗаписи":"2019-04-05"}}},{"@attributes":{"КодОКВЭД":"46.18.14","НаимОКВЭД":"Деятельность агентов, специализирующихся на оптовой торговле чистящими средствами","ПрВерсОКВЭД":"2014"},"ГРНДата":{"@attributes":{"ГРН":"2197456353246","ДатаЗаписи":"2019-04-05"}}},{"@attributes":{"КодОКВЭД":"46.18.3","НаимОКВЭД":"Деятельность агентов, специализирующихся на оптовой торговле техникой, оборудованием и инструментами, применяемыми в медицинских целях","ПрВерсОКВЭД":"2014"},"ГРНДата":{"@attributes":{"ГРН":"2197456353246","ДатаЗаписи":"2019-04-05"}}},{"@attributes":{"КодОКВЭД":"46.19","НаимОКВЭД":"Деятельность агентов по оптовой торговле универсальным ассортиментом товаров","ПрВерсОКВЭД":"2014"},"ГРНДата":{"@attributes":{"ГРН":"2197456353246","ДатаЗаписи":"2019-04-05"}}},{"@attributes":{"КодОКВЭД":"46.46","НаимОКВЭД":"Торговля оптовая фармацевтической продукцией","ПрВерсОКВЭД":"2014"},"ГРНДата":{"@attributes":{"ГРН":"2197456353246","ДатаЗаписи":"2019-04-05"}}},{"@attributes":{"КодОКВЭД":"46.46.2","НаимОКВЭД":"Торговля оптовая изделиями, применяемыми в медицинских целях","ПрВерсОКВЭД":"2014"},"ГРНДата":{"@attributes":{"ГРН":"2197456353246","ДатаЗаписи":"2019-04-05"}}},{"@attributes":{"КодОКВЭД":"46.69","НаимОКВЭД":"Торговля оптовая прочими машинами и оборудованием","ПрВерсОКВЭД":"2014"},"ГРНДата":{"@attributes":{"ГРН":"2197456353246","ДатаЗаписи":"2019-04-05"}}},{"@attributes":{"КодОКВЭД":"46.69.9","НаимОКВЭД":"Торговля оптовая прочими машинами, приборами, аппаратурой и оборудованием общепромышленного и специального назначения","ПрВерсОКВЭД":"2014"},"ГРНДата":{"@attributes":{"ГРН":"2197456353246","ДатаЗаписи":"2019-04-05"}}}]},"СвЗапЕГРЮЛ":[{"@attributes":{"ИдЗап":"1027403903658","ГРН":"1027403903658","ДатаЗап":"2002-12-31"},"ВидЗап":{"@attributes":{"КодСПВЗ":"11101","НаимВидЗап":"Внесение в Единый государственный реестр юридических лиц сведений о юридическом лице, зарегистрированном до 1 июля 2002 года"}},"СвРегОрг":{"@attributes":{"КодНО":"7453","НаимНО":"Инспекция Министерства Российской Федерации по налогам и сборам по Центральному району г.Челябинска"}},"СвСвид":{"@attributes":{"Серия":"74","Номер":"002182988","ДатаВыдСвид":"2002-12-31"}},"СвСтатусЗап":{"ГРНДатаИспр":[{"@attributes":{"ИдЗап":"2077453074664","ГРН":"2077453074664","ДатаЗап":"2007-03-31"}},{"@attributes":{"ИдЗап":"150000164508116","ГРН":"6187456099022","ДатаЗап":"2018-10-17"}}]}},{"@attributes":{"ИдЗап":"2067453037782","ГРН":"2067453037782","ДатаЗап":"2006-04-04"},"ВидЗап":{"@attributes":{"КодСПВЗ":"13200","НаимВидЗап":"Представление сведений об учете юридического лица в налоговом органе"}},"СвРегОрг":{"@attributes":{"КодНО":"7453","НаимНО":"Инспекция Федеральной налоговой службы по Центральному району г. Челябинска"}}},{"@attributes":{"ИдЗап":"2077453074664","ГРН":"2077453074664","ДатаЗап":"2007-03-31"},"ВидЗап":{"@attributes":{"КодСПВЗ":"15101","НаимВидЗап":"Внесение изменений в сведения о юридическом лице, содержащиеся в Едином государственном реестре юридических лиц, в связи с ошибками, допущенными регистрирующим органом"}},"СвРегОрг":{"@attributes":{"КодНО":"7453","НаимНО":"Инспекция Федеральной налоговой службы по Центральному району г. Челябинска"}},"ГРНДатаИспрПред":{"@attributes":{"ИдЗап":"1027403903658","ГРН":"1027403903658","ДатаЗап":"2002-12-31"}}},{"@attributes":{"ИдЗап":"2097453247043","ГРН":"2097453247043","ДатаЗап":"2009-12-26"},"ВидЗап":{"@attributes":{"КодСПВЗ":"13300","НаимВидЗап":"Представление сведений о регистрации юридического лица в качестве страхователя в территориальном органе Пенсионного фонда Российской Федерации"}},"СвРегОрг":{"@attributes":{"КодНО":"7453","НаимНО":"Инспекция Федеральной налоговой службы по Центральному району г. Челябинска"}}},{"@attributes":{"ИдЗап":"150000019157141","ГРН":"2157453118084","ДатаЗап":"2015-08-25"},"ВидЗап":{"@attributes":{"КодСПВЗ":"12103","НаимВидЗап":"Государственная регистрация изменений, внесенных в устав общества с ограниченной ответственностью в целях приведения его в соответствие с положениями Федерального закона от 30.12.2008 № 312-ФЗ"}},"СвРегОрг":{"@attributes":{"КодНО":"7453","НаимНО":"Инспекция Федеральной налоговой службы по Центральному району г. Челябинска"}},"СведПредДок":[{"НаимДок":"Р13001 ЗАЯВЛЕНИЕ ОБ ИЗМЕНЕНИЯХ, ВНОСИМЫХ В УЧРЕД.ДОКУМЕНТЫ","НомДок":"Б/Н","ДатаДок":"2015-08-18"},{"НаимДок":"ДОКУМЕНТ ОБ ОПЛАТЕ ГОСУДАРСТВЕННОЙ ПОШЛИНЫ","НомДок":"35","ДатаДок":"2015-08-14"},{"НаимДок":"ПОДТВЕРЖДЕНИЕ ВКЛАДА В УК","НомДок":"Б/Н","ДатаДок":"2015-08-13"},{"НаимДок":"ПРОТОКОЛ ОБЩЕГО СОБРАНИЯ УЧАСТНИКОВ ЮЛ","НомДок":"16","ДатаДок":"2015-08-13"},{"НаимДок":"ПРОТОКОЛ ОБЩЕГО СОБРАНИЯ УЧАСТНИКОВ ЮЛ","НомДок":"17","ДатаДок":"2015-08-13"},{"НаимДок":"УСТАВ ЮЛ В НОВОЙ РЕДАКЦИИ","НомДок":"Б/Н","ДатаДок":"2015-08-13"},{"НаимДок":"ДОГОВОР АРЕНДЫ (КОПИЯ)","НомДок":"0231/15","ДатаДок":"2015-08-10"}]},{"@attributes":{"ИдЗап":"150000076230032","ГРН":"6167456139625","ДатаЗап":"2016-07-28"},"ВидЗап":{"@attributes":{"КодСПВЗ":"13400","НаимВидЗап":"Представление сведений о регистрации юридического лица в качестве страхователя в исполнительном органе Фонда социального страхования Российской Федерации"}},"СвРегОрг":{"@attributes":{"КодНО":"7456","НаимНО":"Межрайонная инспекция Федеральной налоговой службы № 17 по Челябинской области"}}},{"@attributes":{"ИдЗап":"150000164508116","ГРН":"6187456099022","ДатаЗап":"2018-10-17"},"ВидЗап":{"@attributes":{"КодСПВЗ":"15101","НаимВидЗап":"Внесение изменений в сведения о юридическом лице, содержащиеся в Едином государственном реестре юридических лиц, в связи с ошибками, допущенными регистрирующим органом"}},"СвРегОрг":{"@attributes":{"КодНО":"7456","НаимНО":"Межрайонная инспекция Федеральной налоговой службы № 17 по Челябинской области"}},"СведПредДок":{"НаимДок":"Решение о внесении изменений в ЕГРЮЛ в связи с допущенными ошибками"},"ГРНДатаИспрПред":{"@attributes":{"ИдЗап":"1027403903658","ГРН":"1027403903658","ДатаЗап":"2002-12-31"}}},{"@attributes":{"ИдЗап":"150000173888490","ГРН":"2197456353246","ДатаЗап":"2019-04-05"},"ВидЗап":{"@attributes":{"КодСПВЗ":"12201","НаимВидЗап":"Изменение сведений о юридическом лице, содержащихся в Едином государственном реестре юридических лиц"}},"СвРегОрг":{"@attributes":{"КодНО":"7456","НаимНО":"Межрайонная инспекция Федеральной налоговой службы № 17 по Челябинской области"}},"СведПредДок":{"НаимДок":"ЗАЯВЛЕНИЕ ПО ФОРМЕ Р14001","НомДок":"Б/Н","ДатаДок":"2019-03-29"}},{"@attributes":{"ИдЗап":"150000182472465","ГРН":"2197456888506","ДатаЗап":"2019-08-30"},"ВидЗап":{"@attributes":{"КодСПВЗ":"12201","НаимВидЗап":"Изменение сведений о юридическом лице, содержащихся в Едином государственном реестре юридических лиц"}},"СвРегОрг":{"@attributes":{"КодНО":"7456","НаимНО":"Межрайонная инспекция Федеральной налоговой службы № 17 по Челябинской области"}},"СведПредДок":{"НаимДок":"ЗАЯВЛЕНИЕ ПО ФОРМЕ Р14001","НомДок":"14613А","ДатаДок":"2019-08-23"}},{"@attributes":{"ИдЗап":"150000238039247","ГРН":"2227400008670","ДатаЗап":"2022-01-01"},"ВидЗап":{"@attributes":{"КодСПВЗ":"13801","НаимВидЗап":"Представление сведений о выдаче или замене документов, удостоверяющих личность гражданина Российской Федерации на территории Российской Федерации"}},"СвРегОрг":{"@attributes":{"КодНО":"7456","НаимНО":"Межрайонная инспекция Федеральной налоговой службы № 17 по Челябинской области"}}},{"@attributes":{"ИдЗап":"150000238039248","ГРН":"2227400008680","ДатаЗап":"2022-01-01"},"ВидЗап":{"@attributes":{"КодСПВЗ":"13801","НаимВидЗап":"Представление сведений о выдаче или замене документов, удостоверяющих личность гражданина Российской Федерации на территории Российской Федерации"}},"СвРегОрг":{"@attributes":{"КодНО":"7456","НаимНО":"Межрайонная инспекция Федеральной налоговой службы № 17 по Челябинской области"}}},{"@attributes":{"ИдЗап":"150000268794577","ГРН":"2227400950742","ДатаЗап":"2022-11-06"},"ВидЗап":{"@attributes":{"КодСПВЗ":"13802","НаимВидЗап":"Представление сведений о регистрации физического лица по месту жительства"}},"СвРегОрг":{"@attributes":{"КодНО":"7456","НаимНО":"Межрайонная инспекция Федеральной налоговой службы № 17 по Челябинской области"}}},{"@attributes":{"ИдЗап":"150000268794578","ГРН":"2227400950753","ДатаЗап":"2022-11-06"},"ВидЗап":{"@attributes":{"КодСПВЗ":"13802","НаимВидЗап":"Представление сведений о регистрации физического лица по месту жительства"}},"СвРегОрг":{"@attributes":{"КодНО":"7456","НаимНО":"Межрайонная инспекция Федеральной налоговой службы № 17 по Челябинской области"}}},{"@attributes":{"ИдЗап":"150000303685098","ГРН":"2247400318328","ДатаЗап":"2024-05-31"},"ВидЗап":{"@attributes":{"КодСПВЗ":"17023","НаимВидЗап":"Внесение в Единый государственный реестр юридических лиц сведений о недостоверности сведений о юридическом лице (результаты проверки достоверности содержащихся в Едином государственном реестре юридических лиц сведений о юридическом лице)"}},"СвРегОрг":{"@attributes":{"КодНО":"7456","НаимНО":"Межрайонная инспекция Федеральной налоговой службы № 17 по Челябинской области"}}},{"@attributes":{"ИдЗап":"150000316104546","ГРН":"2247400794760","ДатаЗап":"2024-12-18"},"ВидЗап":{"@attributes":{"КодСПВЗ":"14141","НаимВидЗап":"Принятие регистрирующим органом решения о предстоящем исключении юридического лица из ЕГРЮЛ (наличие в ЕГРЮЛ сведений о юридическом лице, в отношении которых внесена запись о недостоверности)"}},"СвРегОрг":{"@attributes":{"КодНО":"7456","НаимНО":"Межрайонная инспекция Федеральной налоговой службы № 17 по Челябинской области"}},"СведПредДок":{"НаимДок":"Решение о предстоящем исключении ЮЛ из ЕГРЮЛ","НомДок":"8630","ДатаДок":"2024-12-16"}},{"@attributes":{"ИдЗап":"150000325109365","ГРН":"2257401275822","ДатаЗап":"2025-02-09"},"ВидЗап":{"@attributes":{"КодСПВЗ":"13401","НаимВидЗап":"Представление сведений о регистрации юридического лица в качестве страхователя в Социальном фонде Российской Федерации (обязательное социальное страхование)"}},"СвРегОрг":{"@attributes":{"КодНО":"7456","НаимНО":"Межрайонная инспекция Федеральной налоговой службы № 17 по Челябинской области"}},"СведПредДок":{"НаимДок":"Сведения о регистрации ЮЛ по ОСС","ДатаДок":"2025-01-23"}},{"@attributes":{"ИдЗап":"150000325109366","ГРН":"2257401275833","ДатаЗап":"2025-02-09"},"ВидЗап":{"@attributes":{"КодСПВЗ":"13301","НаимВидЗап":"Представление сведений о регистрации юридического лица в качестве страхователя в Социальном фонде Российской Федерации (обязательное пенсионное страхование)"}},"СвРегОрг":{"@attributes":{"КодНО":"7456","НаимНО":"Межрайонная инспекция Федеральной налоговой службы № 17 по Челябинской области"}},"СведПредДок":{"НаимДок":"Сведения о регистрации ЮЛ по ОПС","ДатаДок":"2025-01-23"}},{"@attributes":{"ИдЗап":"150000327245453","ГРН":"2257401815383","ДатаЗап":"2025-02-14"},"ВидЗап":{"@attributes":{"КодСПВЗ":"15401","НаимВидЗап":"Внесение изменений в сведения, содержащиеся в Едином государственном реестре юридических лиц, в связи с переименованием (переподчинением) адресных объектов"}},"СвРегОрг":{"@attributes":{"КодНО":"7456","НаимНО":"Межрайонная инспекция Федеральной налоговой службы № 17 по Челябинской области"}}},{"@attributes":{"ИдЗап":"150000331092061","ГРН":"2257402016408","ДатаЗап":"2025-04-03"},"ВидЗап":{"@attributes":{"КодСПВЗ":"14407","НаимВидЗап":"Прекращение юридического лица (исключение из ЕГРЮЛ юридического лица в связи с наличием в ЕГРЮЛ сведений о нем, в отношении которых внесена запись о недостоверности)"}},"СвРегОрг":{"@attributes":{"КодНО":"7456","НаимНО":"Межрайонная инспекция Федеральной налоговой службы № 17 по Челябинской области"}},"СведПредДок":{"НаимДок":"Решение о предстоящем исключении ЮЛ из ЕГРЮЛ","НомДок":"8630","ДатаДок":"2024-12-16"}},{"@attributes":{"ИдЗап":"150000331092288","ГРН":"2257402017651","ДатаЗап":"2025-04-03"},"ВидЗап":{"@attributes":{"КодСПВЗ":"13200","НаимВидЗап":"Представление сведений об учете юридического лица в налоговом органе"}},"СвРегОрг":{"@attributes":{"КодНО":"7456","НаимНО":"Межрайонная инспекция Федеральной налоговой службы № 17 по Челябинской области"}}}]}}