{"СвЮЛ":{"@attributes":{"ДатаВып":"2025-01-12","ОГРН":"1077536001432","ДатаОГРН":"2007-01-16","ИНН":"7536077632","КПП":"753601001","СпрОПФ":"ОКОПФ","КодОПФ":"12300","ПолнНаимОПФ":"Общества с ограниченной ответственностью"},"СвНаимЮЛ":{"@attributes":{"НаимЮЛПолн":"ОБЩЕСТВО С ОГРАНИЧЕННОЙ ОТВЕТСТВЕННОСТЬЮ \"СПЕЦМОНТАЖ\""},"ГРНДата":{"@attributes":{"ГРН":"1077536001432","ДатаЗаписи":"2007-01-16"}},"СвНаимЮЛСокр":{"@attributes":{"НаимСокр":"ООО \"СПЕЦМОНТАЖ\""},"ГРНДата":{"@attributes":{"ГРН":"1077536001432","ДатаЗаписи":"2007-01-16"}}}},"СвАдресЮЛ":{"@attributes":{"ВидАдрКлассиф":"2"},"АдресРФ":{"@attributes":{"Индекс":"672000","КодРегион":"75","КодАдрКладр":"750000010000586","Дом":"Д.24","Кварт":"ОФИС 1"},"Регион":{"@attributes":{"НаимРегион":"ЗАБАЙКАЛЬСКИЙ КРАЙ"}},"Город":{"@attributes":{"ТипГород":"Г.","НаимГород":"ЧИТА"}},"Улица":{"@attributes":{"ТипУлица":"УЛ.","НаимУлица":"ЧАЙКОВСКОГО"}},"ГРНДата":{"@attributes":{"ГРН":"2137536020620","ДатаЗаписи":"2013-02-20"}}}},"СвОбрЮЛ":{"@attributes":{"ОГРН":"1077536001432","ДатаОГРН":"2007-01-16"},"СпОбрЮЛ":{"@attributes":{"КодСпОбрЮЛ":"11","НаимСпОбрЮЛ":"Создание юридического лица"}},"ГРНДата":{"@attributes":{"ГРН":"1077536001432","ДатаЗаписи":"2007-01-16"}}},"СвРегОрг":{"@attributes":{"КодНО":"7500","НаимНО":"Управление Федеральной налоговой службы по Забайкальскому краю","АдрРО":",672000, Забайкальский край,,г.Чита,, ул. Анохина, 63,,"},"ГРНДата":{"@attributes":{"ГРН":"2217500138315","ДатаЗаписи":"2021-11-25"}}},"СвУчетНО":{"@attributes":{"ИНН":"7536077632","КПП":"753601001","ДатаПостУч":"2021-11-29"},"СвНО":{"@attributes":{"КодНО":"7500","НаимНО":"Управление Федеральной налоговой службы по Забайкальскому краю"}},"ГРНДата":{"@attributes":{"ГРН":"2217500596432","ДатаЗаписи":"2021-11-30"}}},"СвРегПФ":{"@attributes":{"РегНомПФ":"1066008481","ДатаРег":"2007-01-17"},"СвОргПФ":{"@attributes":{"КодПФ":"075","НаимПФ":"Отделение Фонда пенсионного и социального страхования Российской Федерации по Забайкальскому краю"}},"ГРНДата":{"@attributes":{"ГРН":"2257500013880","ДатаЗаписи":"2025-01-12"}}},"СвРегФСС":{"@attributes":{"РегНомФСС":"1066008481","ДатаРег":"2007-01-18"},"СвОргФСС":{"@attributes":{"КодФСС":"075","НаимФСС":"Отделение Фонда пенсионного и социального страхования Российской Федерации по Забайкальскому краю"}},"ГРНДата":{"@attributes":{"ГРН":"2257500013879","ДатаЗаписи":"2025-01-12"}}},"СвУстКап":{"@attributes":{"НаимВидКап":"УСТАВНЫЙ КАПИТАЛ","СумКап":"20000"},"ГРНДата":{"@attributes":{"ГРН":"2197536157828","ДатаЗаписи":"2019-07-05"}}},"СведДолжнФЛ":{"ГРНДатаПерв":{"@attributes":{"ГРН":"2077536114819","ДатаЗаписи":"2007-07-12"}},"СвФЛ":{"@attributes":{"Фамилия":"БАЙКАЛОВА","Имя":"ТАТЬЯНА","Отчество":"МИХАЙЛОВНА","ИННФЛ":"753503261301"},"ГРНДата":{"@attributes":{"ГРН":"2207500106856","ДатаЗаписи":"2020-09-27"}}},"СвДолжн":{"@attributes":{"ВидДолжн":"02","НаимВидДолжн":"Руководитель юридического лица","НаимДолжн":"ГЕНЕРАЛЬНЫЙ ДИРЕКТОР"},"ГРНДата":{"@attributes":{"ГРН":"2207500106856","ДатаЗаписи":"2020-09-27"}}},"СвПолФЛ":{"@attributes":{"Пол":"2"},"ГРНДата":{"@attributes":{"ГРН":"2207500106856","ДатаЗаписи":"2020-09-27"}}},"СвГраждФЛ":{"@attributes":{"КодГражд":"1"},"ГРНДата":{"@attributes":{"ГРН":"2207500106856","ДатаЗаписи":"2020-09-27"}}}},"СвУчредит":{"УчрФЛ":{"ГРНДатаПерв":{"@attributes":{"ГРН":"2197536157828","ДатаЗаписи":"2019-07-05"}},"СвФЛ":{"@attributes":{"Фамилия":"БАЙКАЛОВА","Имя":"ТАТЬЯНА","Отчество":"МИХАЙЛОВНА","ИННФЛ":"753503261301"},"ГРНДата":{"@attributes":{"ГРН":"2207500106856","ДатаЗаписи":"2020-09-27"}}},"СвПолФЛ":{"@attributes":{"Пол":"2"},"ГРНДата":{"@attributes":{"ГРН":"2207500106856","ДатаЗаписи":"2020-09-27"}}},"СвГраждФЛ":{"@attributes":{"КодГражд":"1"},"ГРНДата":{"@attributes":{"ГРН":"2207500106856","ДатаЗаписи":"2020-09-27"}}},"ДоляУстКап":{"@attributes":{"НоминСтоим":"20000"},"РазмерДоли":{"Процент":"100"},"ГРНДата":{"@attributes":{"ГРН":"2207500010298","ДатаЗаписи":"2020-02-05"}}}}},"СвОКВЭД":{"СвОКВЭДОсн":{"@attributes":{"КодОКВЭД":"43.21","НаимОКВЭД":"Производство электромонтажных работ","ПрВерсОКВЭД":"2014"},"ГРНДата":{"@attributes":{"ГРН":"1077536001432","ДатаЗаписи":"2007-01-16"}}},"СвОКВЭДДоп":[{"@attributes":{"КодОКВЭД":"33.14","НаимОКВЭД":"Ремонт электрического оборудования","ПрВерсОКВЭД":"2014"},"ГРНДата":{"@attributes":{"ГРН":"1077536001432","ДатаЗаписи":"2007-01-16"}}},{"@attributes":{"КодОКВЭД":"33.20","НаимОКВЭД":"Монтаж промышленных машин и оборудования","ПрВерсОКВЭД":"2014"},"ГРНДата":{"@attributes":{"ГРН":"1077536001432","ДатаЗаписи":"2007-01-16"}}},{"@attributes":{"КодОКВЭД":"41.2","НаимОКВЭД":"Строительство жилых и нежилых зданий","ПрВерсОКВЭД":"2014"},"ГРНДата":{"@attributes":{"ГРН":"1077536001432","ДатаЗаписи":"2007-01-16"}}},{"@attributes":{"КодОКВЭД":"43.12","НаимОКВЭД":"Подготовка строительной площадки","ПрВерсОКВЭД":"2014"},"ГРНДата":{"@attributes":{"ГРН":"1077536001432","ДатаЗаписи":"2007-01-16"}}},{"@attributes":{"КодОКВЭД":"43.2","НаимОКВЭД":"Производство электромонтажных, санитарно-технических и прочих строительно-монтажных работ","ПрВерсОКВЭД":"2014"},"ГРНДата":{"@attributes":{"ГРН":"1077536001432","ДатаЗаписи":"2007-01-16"}}},{"@attributes":{"КодОКВЭД":"43.3","НаимОКВЭД":"Работы строительные отделочные","ПрВерсОКВЭД":"2014"},"ГРНДата":{"@attributes":{"ГРН":"1077536001432","ДатаЗаписи":"2007-01-16"}}},{"@attributes":{"КодОКВЭД":"84.24","НаимОКВЭД":"Деятельность по обеспечению общественного порядка и безопасности","ПрВерсОКВЭД":"2014"},"ГРНДата":{"@attributes":{"ГРН":"2117536010997","ДатаЗаписи":"2011-02-22"}}},{"@attributes":{"КодОКВЭД":"95.12","НаимОКВЭД":"Ремонт коммуникационного оборудования","ПрВерсОКВЭД":"2014"},"ГРНДата":{"@attributes":{"ГРН":"1077536001432","ДатаЗаписи":"2007-01-16"}}}]},"СвЛицензия":{"@attributes":{"НомЛиц":"75-Б/00010","ДатаЛиц":"2014-04-21","ДатаНачЛиц":"2014-04-21"},"НаимЛицВидДеят":"Деятельность по монтажу, техническому обслуживанию и ремонту средств обеспечения пожарной безопасности зданий и сооружений","ЛицОргВыдЛиц":"Главное управление МЧС России по Забайкальскому краю","ГРНДата":{"@attributes":{"ГРН":"2177536030813","ДатаЗаписи":"2017-01-09"}}},"СвЗапЕГРЮЛ":[{"@attributes":{"ИдЗап":"1077536001432","ГРН":"1077536001432","ДатаЗап":"2007-01-16"},"ВидЗап":{"@attributes":{"КодСПВЗ":"11201","НаимВидЗап":"Создание юридического лица"}},"СвРегОрг":{"@attributes":{"КодНО":"7536","НаимНО":"Межрайонная инспекция Федеральной налоговой службы № 2 по г. Чите"}},"СведПредДок":[{"НаимДок":"ЗАЯВЛЕНИЕ О ГОСУДАРСТВЕННОЙ РЕГИСТРАЦИИ ЮРИДИЧЕСКОГО ЛИЦА ПРИ СОЗДАНИИ"},{"НаимДок":"УСТАВ ЮРИДИЧЕСКОГО ЛИЦА"},{"НаимДок":"УЧРЕДИТЕЛЬНЫЙ ДОГОВОР ЮРИДИЧЕСКОГО ЛИЦА"},{"НаимДок":"ПРОТОКОЛ"},{"НаимДок":"ДОКУМЕНТ ОБ УПЛАТЕ ГОСУДАРСТВЕННОЙ ПОШЛИНЫ","НомДок":"96098350","ДатаДок":"2007-01-10"}],"СвСвид":{"@attributes":{"Серия":"75","Номер":"001810629","ДатаВыдСвид":"2007-01-16"}}},{"@attributes":{"ИдЗап":"2077536008999","ГРН":"2077536008999","ДатаЗап":"2007-01-16"},"ВидЗап":{"@attributes":{"КодСПВЗ":"13200","НаимВидЗап":"Представление сведений об учете юридического лица в налоговом органе"}},"СвРегОрг":{"@attributes":{"КодНО":"7536","НаимНО":"Межрайонная инспекция Федеральной налоговой службы № 2 по г. Чите"}}},{"@attributes":{"ИдЗап":"2077536014060","ГРН":"2077536014060","ДатаЗап":"2007-01-19"},"ВидЗап":{"@attributes":{"КодСПВЗ":"13300","НаимВидЗап":"Представление сведений о регистрации юридического лица в качестве страхователя в территориальном органе Пенсионного фонда Российской Федерации"}},"СвРегОрг":{"@attributes":{"КодНО":"7536","НаимНО":"Межрайонная инспекция Федеральной налоговой службы № 2 по г. Чите"}}},{"@attributes":{"ИдЗап":"2077536015600","ГРН":"2077536015600","ДатаЗап":"2007-01-22"},"ВидЗап":{"@attributes":{"КодСПВЗ":"13400","НаимВидЗап":"Представление сведений о регистрации юридического лица в качестве страхователя в исполнительном органе Фонда социального страхования Российской Федерации"}},"СвРегОрг":{"@attributes":{"КодНО":"7536","НаимНО":"Межрайонная инспекция Федеральной налоговой службы № 2 по г. Чите"}}},{"@attributes":{"ИдЗап":"2077536082028","ГРН":"2077536082028","ДатаЗап":"2007-05-04"},"ВидЗап":{"@attributes":{"КодСПВЗ":"13101","НаимВидЗап":"Представление лицензирующим органом сведений о предоставлении лицензии"}},"СвРегОрг":{"@attributes":{"КодНО":"7536","НаимНО":"Межрайонная инспекция Федеральной налоговой службы № 2 по г. Чите"}}},{"@attributes":{"ИдЗап":"2077536114808","ГРН":"2077536114808","ДатаЗап":"2007-07-12"},"ВидЗап":{"@attributes":{"КодСПВЗ":"12101","НаимВидЗап":"Государственная регистрация изменений, внесенных в учредительный документ юридического лица, и внесение изменений в сведения о юридическом лице, содержащиеся в ЕГРЮЛ"}},"СвРегОрг":{"@attributes":{"КодНО":"7536","НаимНО":"Межрайонная инспекция Федеральной налоговой службы № 2 по г. Чите"}},"СведПредДок":[{"НаимДок":"ЗАЯВЛЕНИЕ О ГОСУДАРСТВЕННОЙ РЕГИСТРАЦИИ ИЗМЕНЕНИЙ, ВНОСИМЫХ В УЧРЕДИТЕЛЬНЫЕ ДОКУМЕНТЫ  ЮРИДИЧЕСКОГО ЛИЦА"},{"НаимДок":"УСТАВ ЮРИДИЧЕСКОГО ЛИЦА"},{"НаимДок":"ПРОТОКОЛ","НомДок":"1","ДатаДок":"2007-07-05"},{"НаимДок":"ДОКУМЕНТ ОБ УПЛАТЕ ГОСУДАРСТВЕННОЙ ПОШЛИНЫ","НомДок":"151692806","ДатаДок":"2007-07-06"}],"СвСвид":{"@attributes":{"Серия":"75","Номер":"001815054","ДатаВыдСвид":"2007-07-12"}}},{"@attributes":{"ИдЗап":"2077536114819","ГРН":"2077536114819","ДатаЗап":"2007-07-12"},"ВидЗап":{"@attributes":{"КодСПВЗ":"12201","НаимВидЗап":"Изменение сведений о юридическом лице, содержащихся в Едином государственном реестре юридических лиц"}},"СвРегОрг":{"@attributes":{"КодНО":"7536","НаимНО":"Межрайонная инспекция Федеральной налоговой службы № 2 по г. Чите"}},"СведПредДок":{"НаимДок":"ЗАЯВЛЕНИЕ О ВНЕСЕНИИ В ЕДИНЫЙ ГОСУДАРСТВЕННЫЙ РЕЕСТР ЮРИДИЧЕСКИХ ЛИЦ ИЗМЕНЕНИЙ В СВЕДЕНИЯ О ЮРИДИЧЕСКОМ ЛИЦЕ, НЕ СВЯЗАННЫХ С ВНЕСЕНИЕМ ИЗМЕНЕНИЙ В УЧРЕДИТЕЛЬНЫЕ ДОКУМЕНТЫ","ДатаДок":"2007-07-09"},"СвСвид":{"@attributes":{"Серия":"75","Номер":"001815055","ДатаВыдСвид":"2007-07-12"}}},{"@attributes":{"ИдЗап":"2107536127928","ГРН":"2107536127928","ДатаЗап":"2010-08-12"},"ВидЗап":{"@attributes":{"КодСПВЗ":"12103","НаимВидЗап":"Государственная регистрация изменений, внесенных в устав общества с ограниченной ответственностью в целях приведения его в соответствие с положениями Федерального закона от 30.12.2008 № 312-ФЗ"}},"СвРегОрг":{"@attributes":{"КодНО":"7536","НаимНО":"Межрайонная инспекция Федеральной налоговой службы № 2 по г. Чите"}},"СведПредДок":[{"НаимДок":"ЗАЯВЛЕНИЕ О ГОСУДАРСТВЕННОЙ РЕГИСТРАЦИИ ИЗМЕНЕНИЙ, ВНОСИМЫХ В УЧРЕДИТЕЛЬНЫЕ ДОКУМЕНТЫ  ЮРИДИЧЕСКОГО ЛИЦА","НомДок":"3319","ДатаДок":"2010-08-05"},{"НаимДок":"ДОКУМЕНТ ОБ УПЛАТЕ ГОСУДАРСТВЕННОЙ ПОШЛИНЫ","ДатаДок":"2010-07-26"},{"НаимДок":"РЕШЕНИЕ","ДатаДок":"2010-07-29"},{"НаимДок":"УСТАВ","ДатаДок":"2010-07-29"}],"СвСвид":{"@attributes":{"Серия":"75","Номер":"002158614","ДатаВыдСвид":"2010-08-12"}}},{"@attributes":{"ИдЗап":"2107536131041","ГРН":"2107536131041","ДатаЗап":"2010-08-20"},"ВидЗап":{"@attributes":{"КодСПВЗ":"12201","НаимВидЗап":"Изменение сведений о юридическом лице, содержащихся в Едином государственном реестре юридических лиц"}},"СвРегОрг":{"@attributes":{"КодНО":"7536","НаимНО":"Межрайонная инспекция Федеральной налоговой службы № 2 по г. Чите"}},"СведПредДок":{"НаимДок":"ЗАЯВЛЕНИЕ О ВНЕСЕНИИ В ЕДИНЫЙ ГОСУДАРСТВЕННЫЙ РЕЕСТР ЮРИДИЧЕСКИХ ЛИЦ ИЗМЕНЕНИЙ В СВЕДЕНИЯ О ЮРИДИЧЕСКОМ ЛИЦЕ, НЕ СВЯЗАННЫХ С ВНЕСЕНИЕМ ИЗМЕНЕНИЙ В УЧРЕДИТЕЛЬНЫЕ ДОКУМЕНТЫ","НомДок":"3428","ДатаДок":"2010-08-13"},"СвСвид":{"@attributes":{"Серия":"75","Номер":"002158744","ДатаВыдСвид":"2010-08-20"}}},{"@attributes":{"ИдЗап":"2117536010997","ГРН":"2117536010997","ДатаЗап":"2011-02-22"},"ВидЗап":{"@attributes":{"КодСПВЗ":"12101","НаимВидЗап":"Государственная регистрация изменений, внесенных в учредительный документ юридического лица, и внесение изменений в сведения о юридическом лице, содержащиеся в ЕГРЮЛ"}},"СвРегОрг":{"@attributes":{"КодНО":"7536","НаимНО":"Межрайонная инспекция Федеральной налоговой службы № 2 по г. Чите"}},"СведПредДок":[{"НаимДок":"ЗАЯВЛЕНИЕ О ГОСУДАРСТВЕННОЙ РЕГИСТРАЦИИ ИЗМЕНЕНИЙ, ВНОСИМЫХ В УЧРЕДИТЕЛЬНЫЕ ДОКУМЕНТЫ  ЮРИДИЧЕСКОГО ЛИЦА","НомДок":"470","ДатаДок":"2011-02-15"},{"НаимДок":"ДОКУМЕНТ ОБ УПЛАТЕ ГОСУДАРСТВЕННОЙ ПОШЛИНЫ","ДатаДок":"2011-02-14"},{"НаимДок":"УСТАВ","ДатаДок":"2011-02-14"},{"НаимДок":"РЕШЕНИЕ","ДатаДок":"2011-02-14"}],"СвСвид":{"@attributes":{"Серия":"75","Номер":"002198315","ДатаВыдСвид":"2011-02-22"}}},{"@attributes":{"ИдЗап":"2137536020620","ГРН":"2137536020620","ДатаЗап":"2013-02-20"},"ВидЗап":{"@attributes":{"КодСПВЗ":"12101","НаимВидЗап":"Государственная регистрация изменений, внесенных в учредительный документ юридического лица, и внесение изменений в сведения о юридическом лице, содержащиеся в ЕГРЮЛ"}},"СвРегОрг":{"@attributes":{"КодНО":"7536","НаимНО":"Межрайонная инспекция Федеральной налоговой службы № 2 по г. Чите"}},"СведПредДок":[{"НаимДок":"ЗАЯВЛЕНИЕ О ГОСУДАРСТВЕННОЙ РЕГИСТРАЦИИ ИЗМЕНЕНИЙ, ВНОСИМЫХ В УЧРЕДИТЕЛЬНЫЕ ДОКУМЕНТЫ  ЮРИДИЧЕСКОГО ЛИЦА","НомДок":"429","ДатаДок":"2013-02-13"},{"НаимДок":"ДОКУМЕНТ ОБ УПЛАТЕ ГОСУДАРСТВЕННОЙ ПОШЛИНЫ","ДатаДок":"2013-02-13"},{"НаимДок":"РЕШЕНИЕ О ВНЕСЕНИИ ИЗМЕНЕНИЙ В УЧРЕДИТЕЛЬНЫЕ ДОКУМЕНТЫ","ДатаДок":"2013-02-12"},{"НаимДок":"УСТАВ","ДатаДок":"2013-02-12"}],"СвСвид":{"@attributes":{"Серия":"75","Номер":"002292650","ДатаВыдСвид":"2013-02-20"}}},{"@attributes":{"ИдЗап":"147536628000141","ГРН":"2147536047888","ДатаЗап":"2014-05-08"},"ВидЗап":{"@attributes":{"КодСПВЗ":"13101","НаимВидЗап":"Представление лицензирующим органом сведений о предоставлении лицензии"}},"СвРегОрг":{"@attributes":{"КодНО":"7536","НаимНО":"Межрайонная инспекция Федеральной налоговой службы № 2 по г. Чите"}},"СведПредДок":{"НаимДок":"Решение о выдаче лицензии"}},{"@attributes":{"ИдЗап":"150000117363154","ГРН":"2177536030813","ДатаЗап":"2017-01-09"},"ВидЗап":{"@attributes":{"КодСПВЗ":"13102","НаимВидЗап":"Представление лицензирующим органом сведений о переоформлении лицензии, внесении изменений в сведения о лицензии (сведений о продлении срока действия лицензии)"}},"СвРегОрг":{"@attributes":{"КодНО":"7536","НаимНО":"Межрайонная инспекция Федеральной налоговой службы № 2 по г. Чите"}}},{"@attributes":{"ИдЗап":"150000176538210","ГРН":"2197536130570","ДатаЗап":"2019-05-19"},"ВидЗап":{"@attributes":{"КодСПВЗ":"13801","НаимВидЗап":"Представление сведений о выдаче или замене документов, удостоверяющих личность гражданина Российской Федерации на территории Российской Федерации"}},"СвРегОрг":{"@attributes":{"КодНО":"7536","НаимНО":"Межрайонная инспекция Федеральной налоговой службы № 2 по г. Чите"}}},{"@attributes":{"ИдЗап":"150000178892999","ГРН":"2197536157828","ДатаЗап":"2019-07-05"},"ВидЗап":{"@attributes":{"КодСПВЗ":"12103","НаимВидЗап":"Государственная регистрация изменений, внесенных в устав общества с ограниченной ответственностью в целях приведения его в соответствие с положениями Федерального закона от 30.12.2008 № 312-ФЗ"}},"СвРегОрг":{"@attributes":{"КодНО":"7536","НаимНО":"Межрайонная инспекция Федеральной налоговой службы № 2 по г. Чите"}},"СведПредДок":[{"НаимДок":"Р13001 ЗАЯВЛЕНИЕ ОБ ИЗМЕНЕНИЯХ, ВНОСИМЫХ В УЧРЕД.ДОКУМЕНТЫ","ДатаДок":"2019-06-28"},{"НаимДок":"УСТАВ ЮЛ В НОВОЙ РЕДАКЦИИ"},{"НаимДок":"РЕШЕНИЕ","НомДок":"3","ДатаДок":"2019-05-23"},{"НаимДок":"КВИТАНЦИЯ","НомДок":"13","ДатаДок":"2019-05-30"},{"НаимДок":"ЗАЯВЛЕНИЕ"}]},{"@attributes":{"ИдЗап":"150000191095163","ГРН":"2207500010298","ДатаЗап":"2020-02-05"},"ВидЗап":{"@attributes":{"КодСПВЗ":"12201","НаимВидЗап":"Изменение сведений о юридическом лице, содержащихся в Едином государственном реестре юридических лиц"}},"СвРегОрг":{"@attributes":{"КодНО":"7536","НаимНО":"Межрайонная инспекция Федеральной налоговой службы № 2 по г. Чите"}},"СведПредДок":{"НаимДок":"ЗАЯВЛЕНИЕ ПО ФОРМЕ Р14001","ДатаДок":"2020-01-29"}},{"@attributes":{"ИдЗап":"150000207843539","ГРН":"2207500106856","ДатаЗап":"2020-09-27"},"ВидЗап":{"@attributes":{"КодСПВЗ":"13801","НаимВидЗап":"Представление сведений о выдаче или замене документов, удостоверяющих личность гражданина Российской Федерации на территории Российской Федерации"}},"СвРегОрг":{"@attributes":{"КодНО":"7536","НаимНО":"Межрайонная инспекция Федеральной налоговой службы № 2 по г. Чите"}}},{"@attributes":{"ИдЗап":"150000235945900","ГРН":"2217500596432","ДатаЗап":"2021-11-30"},"ВидЗап":{"@attributes":{"КодСПВЗ":"13200","НаимВидЗап":"Представление сведений об учете юридического лица в налоговом органе"}},"СвРегОрг":{"@attributes":{"КодНО":"7500","НаимНО":"Управление Федеральной налоговой службы по Забайкальскому краю"}}},{"@attributes":{"ИдЗап":"150000268203163","ГРН":"2227500135333","ДатаЗап":"2022-11-02"},"ВидЗап":{"@attributes":{"КодСПВЗ":"13802","НаимВидЗап":"Представление сведений о регистрации физического лица по месту жительства"}},"СвРегОрг":{"@attributes":{"КодНО":"7500","НаимНО":"Управление Федеральной налоговой службы по Забайкальскому краю"}}},{"@attributes":{"ИдЗап":"150000268203167","ГРН":"2227500135344","ДатаЗап":"2022-11-02"},"ВидЗап":{"@attributes":{"КодСПВЗ":"13802","НаимВидЗап":"Представление сведений о регистрации физического лица по месту жительства"}},"СвРегОрг":{"@attributes":{"КодНО":"7500","НаимНО":"Управление Федеральной налоговой службы по Забайкальскому краю"}}},{"@attributes":{"ИдЗап":"150000318066151","ГРН":"2257500013879","ДатаЗап":"2025-01-12"},"ВидЗап":{"@attributes":{"КодСПВЗ":"13401","НаимВидЗап":"Представление сведений о регистрации юридического лица в качестве страхователя в Социальном фонде Российской Федерации (обязательное социальное страхование)"}},"СвРегОрг":{"@attributes":{"КодНО":"7500","НаимНО":"Управление Федеральной налоговой службы по Забайкальскому краю"}},"СведПредДок":{"НаимДок":"Сведения о регистрации ЮЛ по ОСС","ДатаДок":"2025-01-11"}},{"@attributes":{"ИдЗап":"150000318066152","ГРН":"2257500013880","ДатаЗап":"2025-01-12"},"ВидЗап":{"@attributes":{"КодСПВЗ":"13301","НаимВидЗап":"Представление сведений о регистрации юридического лица в качестве страхователя в Социальном фонде Российской Федерации (обязательное пенсионное страхование)"}},"СвРегОрг":{"@attributes":{"КодНО":"7500","НаимНО":"Управление Федеральной налоговой службы по Забайкальскому краю"}},"СведПредДок":{"НаимДок":"Сведения о регистрации ЮЛ по ОПС","ДатаДок":"2025-01-11"}}]}}