{"СвЮЛ":{"@attributes":{"ДатаВып":"2026-01-31","ОГРН":"1137746065522","ДатаОГРН":"2013-01-31","ИНН":"7729731072","КПП":"525001001","СпрОПФ":"ОКОПФ","КодОПФ":"12300","ПолнНаимОПФ":"Общества с ограниченной ответственностью"},"СвНаимЮЛ":{"@attributes":{"НаимЮЛПолн":"ОБЩЕСТВО С ОГРАНИЧЕННОЙ ОТВЕТСТВЕННОСТЬЮ \"ВЕЛЕС\""},"ГРНДата":{"@attributes":{"ГРН":"1137746065522","ДатаЗаписи":"2013-01-31"}},"СвНаимЮЛСокр":{"@attributes":{"НаимСокр":"ООО \"ВЕЛЕС\""},"ГРНДата":{"@attributes":{"ГРН":"1137746065522","ДатаЗаписи":"2013-01-31"}}}},"СвАдресЮЛ":{"@attributes":{"ВидАдрКлассиф":"1"},"СвМНЮЛ":{"@attributes":{"ИдНом":"604a8470-4c8e-4f93-847d-cc5365520b16"},"Регион":"52","НаимРегион":"НИЖЕГОРОДСКАЯ ОБЛАСТЬ","МуниципРайон":{"@attributes":{"ВидКод":"2","Наим":"ГОРОД НИЖНИЙ НОВГОРОД"}},"НаселенПункт":{"@attributes":{"Вид":"Д.","Наим":"АФОНИНО"}},"ГРНДата":{"@attributes":{"ГРН":"2225200759496","ДатаЗаписи":"2022-10-03"}}},"СвАдрЮЛФИАС":{"@attributes":{"ИдНом":"32dcab53-6ec8-4c54-8829-a47dcf297f92","Индекс":"603087"},"Регион":"52","НаимРегион":"НИЖЕГОРОДСКАЯ ОБЛАСТЬ","МуниципРайон":{"@attributes":{"ВидКод":"2","Наим":"ГОРОД НИЖНИЙ НОВГОРОД"}},"НаселенПункт":{"@attributes":{"Вид":"Д.","Наим":"АФОНИНО"}},"ЭлУлДорСети":{"@attributes":{"Тип":"УЛ","Наим":"КАЗАНСКОЕ ШОССЕ"}},"Здание":{"@attributes":{"Тип":"СТР.","Номер":"25/3"}},"ПомещЗдания":{"@attributes":{"Тип":"ОФИС","Номер":"402"}},"ГРНДата":{"@attributes":{"ГРН":"2225200759496","ДатаЗаписи":"2022-10-03"}},"ГРНДатаИспр":{"@attributes":{"ГРН":"2265200046021","ДатаЗаписи":"2026-01-29"}}},"АдресРФ":{"@attributes":{"Индекс":"603087","КодРегион":"52","КодАдрКладр":"520000010600023","Дом":"СТР. 25/3","Кварт":"ОФИС 402"},"Регион":{"@attributes":{"НаимРегион":"НИЖЕГОРОДСКАЯ ОБЛАСТЬ"}},"Город":{"@attributes":{"ТипГород":"Г","НаимГород":"НИЖНИЙ НОВГОРОД"}},"НаселПункт":{"@attributes":{"ТипНаселПункт":"Д.","НаимНаселПункт":"АФОНИНО"}},"Улица":{"@attributes":{"ТипУлица":"УЛ","НаимУлица":"КАЗАНСКОЕ ШОССЕ"}},"ГРНДата":{"@attributes":{"ГРН":"2225200759496","ДатаЗаписи":"2022-10-03"}},"ГРНДатаИспр":{"@attributes":{"ГРН":"2265200046021","ДатаЗаписи":"2026-01-29"}}}},"СвОбрЮЛ":{"@attributes":{"ОГРН":"1137746065522","ДатаОГРН":"2013-01-31"},"СпОбрЮЛ":{"@attributes":{"КодСпОбрЮЛ":"11","НаимСпОбрЮЛ":"Создание юридического лица"}},"ГРНДата":{"@attributes":{"ГРН":"1137746065522","ДатаЗаписи":"2013-01-31"}}},"СвРегОрг":{"@attributes":{"КодНО":"5275","НаимНО":"Межрайонная инспекция Федеральной налоговой службы № 15 по Нижегородской области","АдрРО":",603155,,, Нижний Новгород г,, Фрунзе ул, д 7,,"},"ГРНДата":{"@attributes":{"ГРН":"2225200759529","ДатаЗаписи":"2022-10-03"}}},"СвСтатус":{"СвСтатус":{"@attributes":{"КодСтатусЮЛ":"114","НаимСтатусЮЛ":"В отношении юридического лица в деле о несостоятельности (банкротстве) введено наблюдение"}},"ГРНДата":{"@attributes":{"ГРН":"2265200058913","ДатаЗаписи":"2026-01-31"}}},"СвУчетНО":{"@attributes":{"ИНН":"7729731072","КПП":"525001001","ДатаПостУч":"2022-10-03"},"СвНО":{"@attributes":{"КодНО":"5250","НаимНО":"Межрайонная инспекция Федеральной налоговой службы № 6 по Нижегородской области"}},"ГРНДата":{"@attributes":{"ГРН":"2225200759518","ДатаЗаписи":"2022-10-03"}}},"СвРегПФ":{"@attributes":{"РегНомПФ":"1058039965","ДатаРег":"2022-10-04"},"СвОргПФ":{"@attributes":{"КодПФ":"052","НаимПФ":"Отделение Фонда пенсионного и социального страхования Российской Федерации по Нижегородской области"}},"ГРНДата":{"@attributes":{"ГРН":"2255201309944","ДатаЗаписи":"2025-02-12"}}},"СвРегФСС":{"@attributes":{"РегНомФСС":"1058039965","ДатаРег":"2022-10-03"},"СвОргФСС":{"@attributes":{"КодФСС":"052","НаимФСС":"Отделение Фонда пенсионного и социального страхования Российской Федерации по Нижегородской области"}},"ГРНДата":{"@attributes":{"ГРН":"2255201310010","ДатаЗаписи":"2025-02-12"}}},"СвУстКап":{"@attributes":{"НаимВидКап":"УСТАВНЫЙ КАПИТАЛ","СумКап":"10000"},"ГРНДата":{"@attributes":{"ГРН":"1137746065522","ДатаЗаписи":"2013-01-31"}}},"СведДолжнФЛ":{"ГРНДатаПерв":{"@attributes":{"ГРН":"2227705867024","ДатаЗаписи":"2022-06-24"}},"СвФЛ":{"@attributes":{"Фамилия":"БУЙНЫЙ","Имя":"АНДРЕЙ","Отчество":"ПЕТРОВИЧ","ИННФЛ":"526016832837"},"ГРНДата":{"@attributes":{"ГРН":"2227705867024","ДатаЗаписи":"2022-06-24"}}},"СвДолжн":{"@attributes":{"ВидДолжн":"02","НаимВидДолжн":"Руководитель юридического лица","НаимДолжн":"ГЕНЕРАЛЬНЫЙ ДИРЕКТОР"},"ГРНДата":{"@attributes":{"ГРН":"2227705867024","ДатаЗаписи":"2022-06-24"}}},"СвПолФЛ":{"@attributes":{"Пол":"1"},"ГРНДата":{"@attributes":{"ГРН":"2227705867024","ДатаЗаписи":"2022-06-24"}}},"СвГраждФЛ":{"@attributes":{"КодГражд":"1"},"ГРНДата":{"@attributes":{"ГРН":"2227705867024","ДатаЗаписи":"2022-06-24"}}}},"СвУчредит":{"УчрФЛ":{"ГРНДатаПерв":{"@attributes":{"ГРН":"2235200094985","ДатаЗаписи":"2023-01-18"}},"СвФЛ":{"@attributes":{"Фамилия":"БУЙНЫЙ","Имя":"АНДРЕЙ","Отчество":"ПЕТРОВИЧ","ИННФЛ":"526016832837"},"ГРНДата":{"@attributes":{"ГРН":"2235200094985","ДатаЗаписи":"2023-01-18"}}},"СвПолФЛ":{"@attributes":{"Пол":"1"},"ГРНДата":{"@attributes":{"ГРН":"2235200094985","ДатаЗаписи":"2023-01-18"}}},"СвГраждФЛ":{"@attributes":{"КодГражд":"1"},"ГРНДата":{"@attributes":{"ГРН":"2235200094985","ДатаЗаписи":"2023-01-18"}}},"ДоляУстКап":{"@attributes":{"НоминСтоим":"5100"},"РазмерДоли":{"Процент":"51"},"ГРНДата":{"@attributes":{"ГРН":"2235200094985","ДатаЗаписи":"2023-01-18"}}}}},"СвДоляООО":{"@attributes":{"НоминСтоим":"4900"},"РазмерДоли":{"Процент":"49"},"ГРНДата":{"@attributes":{"ГРН":"2255201231338","ДатаЗаписи":"2025-02-10"}}},"СвОКВЭД":{"СвОКВЭДОсн":{"@attributes":{"КодОКВЭД":"41.2","НаимОКВЭД":"Строительство жилых и нежилых зданий","ПрВерсОКВЭД":"2014"},"ГРНДата":{"@attributes":{"ГРН":"1137746065522","ДатаЗаписи":"2013-01-31"}}},"СвОКВЭДДоп":[{"@attributes":{"КодОКВЭД":"43.12","НаимОКВЭД":"Подготовка строительной площадки","ПрВерсОКВЭД":"2014"},"ГРНДата":{"@attributes":{"ГРН":"1137746065522","ДатаЗаписи":"2013-01-31"}}},{"@attributes":{"КодОКВЭД":"43.2","НаимОКВЭД":"Производство электромонтажных, санитарно-технических и прочих строительно-монтажных работ","ПрВерсОКВЭД":"2014"},"ГРНДата":{"@attributes":{"ГРН":"1137746065522","ДатаЗаписи":"2013-01-31"}}},{"@attributes":{"КодОКВЭД":"43.3","НаимОКВЭД":"Работы строительные отделочные","ПрВерсОКВЭД":"2014"},"ГРНДата":{"@attributes":{"ГРН":"1137746065522","ДатаЗаписи":"2013-01-31"}}},{"@attributes":{"КодОКВЭД":"46.4","НаимОКВЭД":"Торговля оптовая непродовольственными потребительскими товарами","ПрВерсОКВЭД":"2014"},"ГРНДата":{"@attributes":{"ГРН":"1137746065522","ДатаЗаписи":"2013-01-31"}}},{"@attributes":{"КодОКВЭД":"46.7","НаимОКВЭД":"Торговля оптовая специализированная прочая","ПрВерсОКВЭД":"2014"},"ГРНДата":{"@attributes":{"ГРН":"1137746065522","ДатаЗаписи":"2013-01-31"}}},{"@attributes":{"КодОКВЭД":"47.5","НаимОКВЭД":"Торговля розничная прочими бытовыми изделиями в специализированных магазинах","ПрВерсОКВЭД":"2014"},"ГРНДата":{"@attributes":{"ГРН":"1137746065522","ДатаЗаписи":"2013-01-31"}}},{"@attributes":{"КодОКВЭД":"47.9","НаимОКВЭД":"Торговля розничная вне магазинов, палаток, рынков","ПрВерсОКВЭД":"2014"},"ГРНДата":{"@attributes":{"ГРН":"1137746065522","ДатаЗаписи":"2013-01-31"}}},{"@attributes":{"КодОКВЭД":"49.3","НаимОКВЭД":"Деятельность прочего сухопутного пассажирского транспорта","ПрВерсОКВЭД":"2014"},"ГРНДата":{"@attributes":{"ГРН":"1137746065522","ДатаЗаписи":"2013-01-31"}}},{"@attributes":{"КодОКВЭД":"70.22","НаимОКВЭД":"Консультирование по вопросам коммерческой деятельности и управления","ПрВерсОКВЭД":"2014"},"ГРНДата":{"@attributes":{"ГРН":"1137746065522","ДатаЗаписи":"2013-01-31"}}}]},"СвЗапЕГРЮЛ":[{"@attributes":{"ИдЗап":"137746528005309","ГРН":"1137746065522","ДатаЗап":"2013-01-31"},"ВидЗап":{"@attributes":{"КодСПВЗ":"11201","НаимВидЗап":"Создание юридического лица"}},"СвРегОрг":{"@attributes":{"КодНО":"7746","НаимНО":"Межрайонная инспекция Федеральной налоговой службы № 46 по г. Москве"}},"СведПредДок":[{"НаимДок":"Р11001 Заявление о создании ЮЛ"},{"НаимДок":"Документ об оплате государственной пошлины","НомДок":"274","ДатаДок":"2013-01-28"},{"НаимДок":"Устав ЮЛ","ДатаДок":"2013-01-25"},{"НаимДок":"Решение о создании ЮЛ","НомДок":"1","ДатаДок":"2013-01-25"},{"НаимДок":"ПРИКАЗ"}],"СвСвид":{"@attributes":{"Серия":"77","Номер":"015346898","ДатаВыдСвид":"2013-02-01"}}},{"@attributes":{"ИдЗап":"137746531010927","ГРН":"2137746644099","ДатаЗап":"2013-01-31"},"ВидЗап":{"@attributes":{"КодСПВЗ":"13200","НаимВидЗап":"Представление сведений об учете юридического лица в налоговом органе"}},"СвРегОрг":{"@attributes":{"КодНО":"7746","НаимНО":"Межрайонная инспекция Федеральной налоговой службы № 46 по г. Москве"}}},{"@attributes":{"ИдЗап":"137746535002299","ГРН":"2137746718349","ДатаЗап":"2013-02-04"},"ВидЗап":{"@attributes":{"КодСПВЗ":"13300","НаимВидЗап":"Представление сведений о регистрации юридического лица в качестве страхователя в территориальном органе Пенсионного фонда Российской Федерации"}},"СвРегОрг":{"@attributes":{"КодНО":"7746","НаимНО":"Межрайонная инспекция Федеральной налоговой службы № 46 по г. Москве"}}},{"@attributes":{"ИдЗап":"137746535002769","ГРН":"2137746722243","ДатаЗап":"2013-02-04"},"ВидЗап":{"@attributes":{"КодСПВЗ":"13400","НаимВидЗап":"Представление сведений о регистрации юридического лица в качестве страхователя в исполнительном органе Фонда социального страхования Российской Федерации"}},"СвРегОрг":{"@attributes":{"КодНО":"7746","НаимНО":"Межрайонная инспекция Федеральной налоговой службы № 46 по г. Москве"}}},{"@attributes":{"ИдЗап":"150000258435867","ГРН":"2227705025491","ДатаЗап":"2022-06-06"},"ВидЗап":{"@attributes":{"КодСПВЗ":"12201","НаимВидЗап":"Изменение сведений о юридическом лице, содержащихся в Едином государственном реестре юридических лиц"}},"СвРегОрг":{"@attributes":{"КодНО":"7746","НаимНО":"Межрайонная инспекция Федеральной налоговой службы № 46 по г. Москве"}},"СведПредДок":{"НаимДок":"Р13014 Заявление об изменении учр.документа и/или иных сведений о ЮЛ"}},{"@attributes":{"ИдЗап":"150000259476870","ГРН":"2227705867024","ДатаЗап":"2022-06-24"},"ВидЗап":{"@attributes":{"КодСПВЗ":"12201","НаимВидЗап":"Изменение сведений о юридическом лице, содержащихся в Едином государственном реестре юридических лиц"}},"СвРегОрг":{"@attributes":{"КодНО":"7746","НаимНО":"Межрайонная инспекция Федеральной налоговой службы № 46 по г. Москве"}},"СведПредДок":[{"НаимДок":"Р13014 Заявление об изменении учр.документа и/или иных сведений о ЮЛ"},{"НаимДок":"Решение о внесении изменений в учредительный документ ЮЛ, либо иное решение или документ, на основании которого вносятся данные изменения"},{"НаимДок":"Иной докум. в соотв.с законодательством РФ"}]},{"@attributes":{"ИдЗап":"150000259951404","ГРН":"2227706180788","ДатаЗап":"2022-07-04"},"ВидЗап":{"@attributes":{"КодСПВЗ":"12201","НаимВидЗап":"Изменение сведений о юридическом лице, содержащихся в Едином государственном реестре юридических лиц"}},"СвРегОрг":{"@attributes":{"КодНО":"7746","НаимНО":"Межрайонная инспекция Федеральной налоговой службы № 46 по г. Москве"}},"СведПредДок":[{"НаимДок":"Р13014 Заявление об изменении учр.документа и/или иных сведений о ЮЛ"},{"НаимДок":"Иной докум. в соотв.с законодательством РФ"}]},{"@attributes":{"ИдЗап":"150000261736865","ГРН":"2227707557625","ДатаЗап":"2022-08-15"},"ВидЗап":{"@attributes":{"КодСПВЗ":"12201","НаимВидЗап":"Изменение сведений о юридическом лице, содержащихся в Едином государственном реестре юридических лиц"}},"СвРегОрг":{"@attributes":{"КодНО":"7746","НаимНО":"Межрайонная инспекция Федеральной налоговой службы № 46 по г. Москве"}},"СведПредДок":[{"НаимДок":"Р13014 Заявление об изменении учр.документа и/или иных сведений о ЮЛ"},{"НаимДок":"Решение о внесении изменений в учредительный документ ЮЛ, либо иное решение или документ, на основании которого вносятся данные изменения"},{"НаимДок":"Иной докум. в соотв.с законодательством РФ"}]},{"@attributes":{"ИдЗап":"150000265078169","ГРН":"2225200759496","ДатаЗап":"2022-10-03"},"ВидЗап":{"@attributes":{"КодСПВЗ":"12101","НаимВидЗап":"Государственная регистрация изменений, внесенных в учредительный документ юридического лица, и внесение изменений в сведения о юридическом лице, содержащиеся в ЕГРЮЛ"}},"СвРегОрг":{"@attributes":{"КодНО":"5275","НаимНО":"Межрайонная инспекция Федеральной налоговой службы № 15 по Нижегородской области"}},"СведПредДок":[{"НаимДок":"Р13014 Заявление об изменении учр.документа и/или иных сведений о ЮЛ","НомДок":"29198А","ДатаДок":"2022-09-26"},{"НаимДок":"ПРОТОКОЛ ОБЩЕГО СОБРАНИЯ УЧАСТНИКОВ ЮЛ","НомДок":"1","ДатаДок":"2022-08-08"},{"НаимДок":"Учредительный документ ЮЛ в новой редакции","ДатаДок":"2022-08-08"},{"НаимДок":"ДОГОВОР АРЕНДЫ","ДатаДок":"2022-06-01"},{"НаимДок":"АКТ ПРИЕМА ПЕРЕДАЧИ"},{"НаимДок":"СОГЛАШЕНИЕ К ДОГОВОРУ","ДатаДок":"2022-08-15"},{"НаимДок":"СВИДЕТЕЛЬСТВО ОБ УДОСТОВЕРЕНИИ РЕШЕНИЯ","ДатаДок":"2022-06-08"},{"НаимДок":"СВИДЕТЕЛЬСТВО О ГОСУДАРСТВЕННОЙ РЕГИСТРАЦИИ"},{"НаимДок":"УВЕДОМЛЕНИЕ"}]},{"@attributes":{"ИдЗап":"150000265374670","ГРН":"2225200759507","ДатаЗап":"2022-10-03"},"ВидЗап":{"@attributes":{"КодСПВЗ":"13200","НаимВидЗап":"Представление сведений об учете юридического лица в налоговом органе"}},"СвРегОрг":{"@attributes":{"КодНО":"5275","НаимНО":"Межрайонная инспекция Федеральной налоговой службы № 15 по Нижегородской области"}}},{"@attributes":{"ИдЗап":"150000265374671","ГРН":"2225200759518","ДатаЗап":"2022-10-03"},"ВидЗап":{"@attributes":{"КодСПВЗ":"13200","НаимВидЗап":"Представление сведений об учете юридического лица в налоговом органе"}},"СвРегОрг":{"@attributes":{"КодНО":"5275","НаимНО":"Межрайонная инспекция Федеральной налоговой службы № 15 по Нижегородской области"}}},{"@attributes":{"ИдЗап":"150000265420900","ГРН":"2225200763270","ДатаЗап":"2022-10-04"},"ВидЗап":{"@attributes":{"КодСПВЗ":"13300","НаимВидЗап":"Представление сведений о регистрации юридического лица в качестве страхователя в территориальном органе Пенсионного фонда Российской Федерации"}},"СвРегОрг":{"@attributes":{"КодНО":"5275","НаимНО":"Межрайонная инспекция Федеральной налоговой службы № 15 по Нижегородской области"}}},{"@attributes":{"ИдЗап":"150000273941006","ГРН":"2235200033022","ДатаЗап":"2023-01-15"},"ВидЗап":{"@attributes":{"КодСПВЗ":"15401","НаимВидЗап":"Внесение изменений в сведения, содержащиеся в Едином государственном реестре юридических лиц, в связи с переименованием (переподчинением) адресных объектов"}},"СвРегОрг":{"@attributes":{"КодНО":"5275","НаимНО":"Межрайонная инспекция Федеральной налоговой службы № 15 по Нижегородской области"}}},{"@attributes":{"ИдЗап":"150000273750301","ГРН":"2235200094985","ДатаЗап":"2023-01-18"},"ВидЗап":{"@attributes":{"КодСПВЗ":"12201","НаимВидЗап":"Изменение сведений о юридическом лице, содержащихся в Едином государственном реестре юридических лиц"}},"СвРегОрг":{"@attributes":{"КодНО":"5275","НаимНО":"Межрайонная инспекция Федеральной налоговой службы № 15 по Нижегородской области"}},"СведПредДок":[{"НаимДок":"Р13014 Заявление об изменении учр.документа и/или иных сведений о ЮЛ","НомДок":"400А","ДатаДок":"2023-01-11"},{"НаимДок":"СВЕДЕНИЯ","ДатаДок":"2023-01-11"}]},{"@attributes":{"ИдЗап":"150000292323481","ГРН":"2235200779207","ДатаЗап":"2023-11-02"},"ВидЗап":{"@attributes":{"КодСПВЗ":"15401","НаимВидЗап":"Внесение изменений в сведения, содержащиеся в Едином государственном реестре юридических лиц, в связи с переименованием (переподчинением) адресных объектов"}},"СвРегОрг":{"@attributes":{"КодНО":"5275","НаимНО":"Межрайонная инспекция Федеральной налоговой службы № 15 по Нижегородской области"}}},{"@attributes":{"ИдЗап":"150000324586972","ГРН":"2255201231338","ДатаЗап":"2025-02-10"},"ВидЗап":{"@attributes":{"КодСПВЗ":"12201","НаимВидЗап":"Изменение сведений о юридическом лице, содержащихся в Едином государственном реестре юридических лиц"}},"СвРегОрг":{"@attributes":{"КодНО":"5275","НаимНО":"Межрайонная инспекция Федеральной налоговой службы № 15 по Нижегородской области"}},"СведПредДок":[{"НаимДок":"Р13014 Заявление об изменении учр.документа и/или иных сведений о ЮЛ"},{"НаимДок":"Иной докум. в соотв.с законодательством РФ"},{"НаимДок":"Иной докум. в соотв.с законодательством РФ"}]},{"@attributes":{"ИдЗап":"150000326165599","ГРН":"2255201309944","ДатаЗап":"2025-02-12"},"ВидЗап":{"@attributes":{"КодСПВЗ":"13301","НаимВидЗап":"Представление сведений о регистрации юридического лица в качестве страхователя в Социальном фонде Российской Федерации (обязательное пенсионное страхование)"}},"СвРегОрг":{"@attributes":{"КодНО":"5275","НаимНО":"Межрайонная инспекция Федеральной налоговой службы № 15 по Нижегородской области"}},"СведПредДок":{"НаимДок":"Сведения о регистрации ЮЛ по ОПС","ДатаДок":"2025-01-23"}},{"@attributes":{"ИдЗап":"150000326165806","ГРН":"2255201310010","ДатаЗап":"2025-02-12"},"ВидЗап":{"@attributes":{"КодСПВЗ":"13401","НаимВидЗап":"Представление сведений о регистрации юридического лица в качестве страхователя в Социальном фонде Российской Федерации (обязательное социальное страхование)"}},"СвРегОрг":{"@attributes":{"КодНО":"5275","НаимНО":"Межрайонная инспекция Федеральной налоговой службы № 15 по Нижегородской области"}},"СведПредДок":{"НаимДок":"Сведения о регистрации ЮЛ по ОСС","ДатаДок":"2025-01-23"}},{"@attributes":{"ИдЗап":"150000327009540","ГРН":"2255201396460","ДатаЗап":"2025-02-14"},"ВидЗап":{"@attributes":{"КодСПВЗ":"15401","НаимВидЗап":"Внесение изменений в сведения, содержащиеся в Едином государственном реестре юридических лиц, в связи с переименованием (переподчинением) адресных объектов"}},"СвРегОрг":{"@attributes":{"КодНО":"5275","НаимНО":"Межрайонная инспекция Федеральной налоговой службы № 15 по Нижегородской области"}}},{"@attributes":{"ИдЗап":"150000333226751","ГРН":"2255201649525","ДатаЗап":"2025-05-08"},"ВидЗап":{"@attributes":{"КодСПВЗ":"15401","НаимВидЗап":"Внесение изменений в сведения, содержащиеся в Едином государственном реестре юридических лиц, в связи с переименованием (переподчинением) адресных объектов"}},"СвРегОрг":{"@attributes":{"КодНО":"5275","НаимНО":"Межрайонная инспекция Федеральной налоговой службы № 15 по Нижегородской области"}}},{"@attributes":{"ИдЗап":"150000359496208","ГРН":"2265200046021","ДатаЗап":"2026-01-29"},"ВидЗап":{"@attributes":{"КодСПВЗ":"15401","НаимВидЗап":"Внесение изменений в сведения, содержащиеся в Едином государственном реестре юридических лиц, в связи с переименованием (переподчинением) адресных объектов"}},"СвРегОрг":{"@attributes":{"КодНО":"5275","НаимНО":"Межрайонная инспекция Федеральной налоговой службы № 15 по Нижегородской области"}}},{"@attributes":{"ИдЗап":"150000359711611","ГРН":"2265200058913","ДатаЗап":"2026-01-31"},"ВидЗап":{"@attributes":{"КодСПВЗ":"14131","НаимВидЗап":"В отношении юридического лица в деле о несостоятельности (банкротстве) введено наблюдение"}},"СвРегОрг":{"@attributes":{"КодНО":"5275","НаимНО":"Межрайонная инспекция Федеральной налоговой службы № 15 по Нижегородской области"}},"СведПредДок":[{"НаимДок":"Сведения из ЕФРСБ о ЮЛ","НомДок":"21349298","ДатаДок":"2026-01-28"},{"НаимДок":"Определение суда о введении наблюдения","НомДок":"А43-33077/2025","ДатаДок":"2026-01-27"}]}]}}